Metadata-Version: 1.1
Name: Flask-Spyne
Version: 0.2
Summary: A Flask extension, provides support for Spyne.
Home-page: http://github.com/rayrapetyan/flask-spyne
Author: Robert Ayrapetyan
Author-email: robert.ayrapetyan@gmail.com
License: BSD
Download-URL: http://pypi.python.org/pypi/Flask-Spyne
Keywords: flask,spyne,soap,wsdl,wsgi,zeromq,rest,rpc,json,http,msgpack,xml,sqlalchemy,werkzeug,yaml
Platform: any
Classifier: Development Status :: 4 - Beta
Classifier: Environment :: Web Environment
Classifier: Intended Audience :: Developers
Classifier: License :: OSI Approved :: BSD License
Classifier: Operating System :: OS Independent
Classifier: Programming Language :: Python
Classifier: Topic :: Internet :: WWW/HTTP
Classifier: Topic :: Software Development :: Libraries :: Python Modules
